setup.py
pollster/__init__.py
pollster/api.py
pollster/api_client.py
pollster/configuration.py
pollster/rest.py
pollster.egg-info/PKG-INFO
pollster.egg-info/SOURCES.txt
pollster.egg-info/dependency_links.txt
pollster.egg-info/requires.txt
pollster.egg-info/top_level.txt
pollster/models/__init__.py
pollster/models/chart.py
pollster/models/chart_estimate.py
pollster/models/chart_estimate_lowess_parameters.py
pollster/models/chart_pollster_estimate_summary.py
pollster/models/inline_response_200.py
pollster/models/inline_response_200_1.py
pollster/models/inline_response_200_2.py
pollster/models/inline_response_200_3.py
pollster/models/inline_response_200_4.py
pollster/models/inline_response_200_5.py
pollster/models/poll.py
pollster/models/poll_question.py
pollster/models/poll_question_responses.py
pollster/models/poll_question_sample_subpopulations.py
pollster/models/question.py
pollster/models/question_responses.py
pollster/models/tag.py