Metadata-Version: 1.0
Name: pollster
Version: 2.0.0
Summary: Pollster API
Home-page: https://github.com/huffpostdata/python-pollster
Author: UNKNOWN
Author-email: Adam Hooper <adam.hooper@huffingtonpost.com>
License: UNKNOWN
Keywords: Pollster API
Platform: UNKNOWN
